{
  "cli": {
    "version": ">= 5.9.2"
  },
  "build": {
    "development": {
      "developmentClient": true,
      "distribution": "internal"
    },
    "preview": {
      "distribution": "internal",
      "android": {
        "buildType": "apk"
      },
      "env": {
        "EXPO_PUBLIC_BATTLE_SERVER_URL": "https://pootime-adventure-battle-server.onrender.com/"
      }
    },
    "production": {
      "env": {
        "EXPO_PUBLIC_BATTLE_SERVER_URL": "https://pootime-adventure-battle-server.onrender.com/"
      }
    }
  },
  "submit": {
    "production": {}
  }
}
